upnote_python_client/__init__.py
upnote_python_client-1.0.0.dist-info/licenses/LICENSE
upnote_python_client-1.0.0.dist-info/METADATA
upnote_python_client-1.0.0.dist-info/WHEEL
upnote_python_client-1.0.0.dist-info/top_level.txt
upnote_python_client-1.0.0.dist-info/RECORD
