Metadata-Version: 2.4
Name: upnote-python-client
Version: 1.0.0
Summary: A Python client for UpNote using URL schemes to create and manage notes
Home-page: https://github.com/upnote-python/upnote-python-client
Author: UpNote Python Client Team
Author-email: UpNote Python Client Team <upnote.python.client@gmail.com>
Maintainer-email: UpNote Python Client Team <upnote.python.client@gmail.com>
License: MIT License
Project-URL: Homepage, https://github.com/upnote-python/upnote-python-client
Project-URL: Documentation, https://github.com/upnote-python/upnote-python-client/blob/main/docs/API_REFERENCE.md
Project-URL: Repository, https://github.com/upnote-python/upnote-python-client
Project-URL: Bug Reports, https://github.com/upnote-python/upnote-python-client/issues
Project-URL: Changelog, https://github.com/upnote-python/upnote-python-client/blob/main/CHANGELOG.md
Keywords: upnote,notes,markdown,productivity,url-scheme,x-callback-url
Classifier: Development Status :: 5 - Production/Stable
Classifier: Intended Audience :: Developers
Classifier: License :: OSI Approved :: MIT License
Classifier: Operating System :: OS Independent
Classifier: Operating System :: MacOS
Classifier: Operating System :: Microsoft :: Windows
Classifier: Operating System :: POSIX :: Linux
Classifier: Programming Language :: Python :: 3
Classifier: Programming Language :: Python :: 3.7
Classifier: Programming Language :: Python :: 3.8
Classifier: Programming Language :: Python :: 3.9
Classifier: Programming Language :: Python :: 3.10
Classifier: Programming Language :: Python :: 3.11
Classifier: Programming Language :: Python :: 3.12
Classifier: Topic :: Office/Business
Classifier: Topic :: Text Processing
Classifier: Topic :: Text Processing :: Markup :: Markdown
Classifier: Topic :: Utilities
Classifier: Topic :: Software Development :: Libraries :: Python Modules
Requires-Python: >=3.7
License-File: LICENSE
Provides-Extra: dev
Requires-Dist: pytest>=6.0; extra == "dev"
Requires-Dist: pytest-cov>=2.0; extra == "dev"
Requires-Dist: black>=21.0; extra == "dev"
Requires-Dist: flake8>=3.8; extra == "dev"
Requires-Dist: twine>=3.0; extra == "dev"
Requires-Dist: wheel>=0.36; extra == "dev"
Dynamic: author
Dynamic: home-page
Dynamic: license-file
Dynamic: requires-python
